owl_results/__init__.py
owl_results/bp/__init__.py
owl_results/bp/owl_results_api.py
owl_results/dmo/__init__.py
owl_results/dmo/edge_dedupe.py
owl_results/dmo/ontology_node_dedupe.py
owl_results/dto/__init__.py
owl_results/dto/typedefs.py
owl_results/svc/__init__.py
owl_results/svc/create_graph_structure.py
owl_results/svc/create_normalized_text.py
owl_results/svc/post_process_structure.py
owl_results-0.1.4.dist-info/METADATA
owl_results-0.1.4.dist-info/WHEEL
owl_results-0.1.4.dist-info/RECORD
